__init__.py
core.py
python_hash-0.1.0.dist-info/METADATA
python_hash-0.1.0.dist-info/WHEEL
python_hash-0.1.0.dist-info/top_level.txt
python_hash-0.1.0.dist-info/RECORD
